README.md
setup.py
fastapicli/__init__.py
fastapicli/api.pyt
fastapicli/fastapi_api.py
fastapicli/fastapi_init.py
fastapicli/logic.pyt
fastapicli.egg-info/PKG-INFO
fastapicli.egg-info/SOURCES.txt
fastapicli.egg-info/dependency_links.txt
fastapicli.egg-info/requires.txt
fastapicli.egg-info/top_level.txt
fastapicli/fastapidemo/Dockerfile
fastapicli/fastapidemo/README.md
fastapicli/fastapidemo/docker-compose-dev.yml
fastapicli/fastapidemo/docker-compose-local.yml
fastapicli/fastapidemo/docker-compose-sb2.yml
fastapicli/fastapidemo/env-backend-dev.env
fastapicli/fastapidemo/env-backend-sb2.env
fastapicli/fastapidemo/env-postgres-dev.env
fastapicli/fastapidemo/env-postgres-sb2.env
fastapicli/fastapidemo/app/README.md
fastapicli/fastapidemo/app/gunicorn_conf.py
fastapicli/fastapidemo/app/main.py
fastapicli/fastapidemo/app/requirements.txt
fastapicli/fastapidemo/app/tests-start.sh
fastapicli/fastapidemo/app/cms/__init__.py
fastapicli/fastapidemo/app/cms/app.py
fastapicli/fastapidemo/app/cms/api/__init__.py
fastapicli/fastapidemo/app/cms/api/user.py
fastapicli/fastapidemo/app/cms/core/__init__.py
fastapicli/fastapidemo/app/cms/core/auth.py
fastapicli/fastapidemo/app/cms/core/config.py
fastapicli/fastapidemo/app/cms/core/db.py
fastapicli/fastapidemo/app/cms/core/error_handler.py
fastapicli/fastapidemo/app/cms/core/logger.py
fastapicli/fastapidemo/app/cms/logic/__init__.py
fastapicli/fastapidemo/app/cms/logic/common/__init__.py
fastapicli/fastapidemo/app/cms/logic/common/crud.py
fastapicli/fastapidemo/app/cms/logic/common/user.py