Metadata-Version: 1.1
Name: fastapicli
Version: 0.0.3
Summary: fastapicli is a easy tool for fastapi orm with jwt
Home-page: http://github.com/comger/fastapicli
Author: comger@gmail.com
Author-email: comger@gmail.com
License: http://www.apache.org/licenses/LICENSE-2.0
Keywords: fastapi,orm,peewee,jwt,codegen
Platform: UNKNOWN
Classifier: License :: OSI Approved :: Apache Software License
Classifier: Programming Language :: Python :: 3
Classifier: Programming Language :: Python :: 3.5
Classifier: Programming Language :: Python :: 3.7
Classifier: Programming Language :: Python :: Implementation :: CPython
Classifier: Programming Language :: Python :: Implementation :: PyPy
